[
  { "21": [] },
  { "74": [["rightElbow", "rightWrist"]] },
  {
    "128": [
      ["rightShoulder", "rightElbow"],
      ["rightElbow", "rightWrist"]
    ]
  },

  { "193": [["nose", "leftEye"]] },

  {
    "250": [
      ["rightElbow", "rightWrist"],
      ["leftElbow", "leftWrist"]
    ]
  },

  {
    "312": [
      ["rightElbow", "rightWrist"],
      ["leftElbow", "leftWrist"]
    ]
  },

  {
    "344": [
      ["leftShoulder", "leftElbow"],
      ["leftElbow", "leftWrist"]
    ]
  },

  { "373": [["rightElbow", "rightWrist"]] },

  {
    "416": [
      ["rightElbow", "rightWrist"],
      ["leftElbow", "leftWrist"]
    ]
  },

  {
    "462": [
      ["nose", "leftEye"],
      ["nose", "rightEye"]
    ]
  },

  { "520": [] },

  {
    "576": [
      ["rightShoulder", "rightElbow"],
      ["leftShoulder", "leftElbow"]
    ]
  },

  { "632": [] },
  {
    "664": [
      ["leftEye", "leftEar"],
      ["rightElbow", "rightWrist"]
    ]
  }
]
